surquest/fastapi/schemas/responses/__init__.py
surquest/fastapi/schemas/responses/base.py
surquest/fastapi/schemas/responses/info.py
surquest/fastapi/schemas/responses/message.py
surquest/fastapi/schemas/responses/metadata.py
surquest/fastapi/schemas/responses/responses.py
surquest/fastapi/schemas/responses/status.py
surquest/fastapi/utils/__init__.py
surquest/fastapi/utils/args.py
surquest/fastapi/utils/auth.py
surquest/fastapi/utils/route.py
surquest/fastapi/utils/GCP/GCP.py
surquest/fastapi/utils/GCP/__init__.py
surquest/fastapi/utils/GCP/catcher.py
surquest/fastapi/utils/GCP/formatter.py
surquest/fastapi/utils/GCP/http_context.py
surquest/fastapi/utils/GCP/logging.py
surquest/fastapi/utils/GCP/middleware.py
surquest/fastapi/utils/GCP/tracer.py
surquest_fastapi_utils-0.2.6.dist-info/METADATA
surquest_fastapi_utils-0.2.6.dist-info/WHEEL
surquest_fastapi_utils-0.2.6.dist-info/licenses/LICENSE
surquest_fastapi_utils-0.2.6.dist-info/RECORD
