Metadata-Version: 2.1
Name: surquest-fastapi-utils
Version: 0.2.6
Summary: This project provides collection of utilities for FastAPI framework as: Catcher, Middleware, etc.
Project-URL: Homepage, https://github.com/surquest/python-fastapi-utils
Project-URL: Bug Tracker, https://github.com/surquest/python-fastapi-utils/issues
Author-email: Michal Švarc <michal.svarc@surquest.com>
License-File: LICENSE
Requires-Dist: fastapi>=0.81.0
Requires-Dist: google-cloud-logging>=3.1.0
Requires-Dist: opentelemetry-exporter-gcp-trace~=1.4.0
Provides-Extra: test
Requires-Dist: pytest-asyncio>=0.20.0; extra == 'test'
Requires-Dist: pytest-cov>=4.0.0; extra == 'test'
Requires-Dist: pytest>=7.2.1; extra == 'test'
Requires-Dist: starlette>=0.24.0; extra == 'test'
